MANIFEST.in
setup.py
KezMenu.egg-info/PKG-INFO
KezMenu.egg-info/SOURCES.txt
KezMenu.egg-info/dependency_links.txt
KezMenu.egg-info/entry_points.txt
KezMenu.egg-info/not-zip-safe
KezMenu.egg-info/top_level.txt
kezmenu/__init__.py
kezmenu/kezmenu.py
kezmenu/kezmenu_effects.py
kezmenu/tests.py
kezmenu/tests_effects.py
kezmenu/docs/CONCLUSIONS.txt
kezmenu/docs/EFFECTS.txt
kezmenu/docs/HISTORY.txt
kezmenu/docs/README.txt