Metadata-Version: 1.1
Name: KezMenu
Version: 0.3.6
Summary: A simple and basical Pygame library for fast develop of menu interfaces
Home-page: http://www.pygame.org/project-KezMenu-996-.html
Author: keul
Author-email: luca@keul.it
License: GPL
Keywords: python pygame menu kezmenu library
Platform: UNKNOWN
Classifier: Development Status :: 7 - Inactive
Classifier: Intended Audience :: Developers
Classifier: License :: OSI Approved :: GNU General Public License (GPL)
Classifier: Operating System :: OS Independent
Classifier: Programming Language :: Python
Classifier: Programming Language :: Python :: 2.6
Classifier: Topic :: Games/Entertainment
Classifier: Topic :: Multimedia :: Graphics
Classifier: Topic :: Software Development :: Libraries :: pygame
Classifier: Topic :: Software Development :: Libraries :: Python Modules
Classifier: Topic :: Software Development :: User Interfaces
